[{"name":"sql.active_record","payload":{"sql":"SELECT \"users\".* FROM \"users\" ","name":"User Load","connection_id":70150201096160,"binds":[]},"time":"2013-07-22T00:39:58-07:00","transaction_id":"c8444315dded90ed8d49","end":"2013-07-22T00:39:58-07:00","duration":0.5289999999999999},{"name":"sql.active_record","payload":{"sql":"SELECT \"languages\".* FROM \"languages\" INNER JOIN \"desired_languages_users\" ON \"languages\".\"id\" = \"desired_languages_users\".\"desired_language_id\" WHERE \"languages\".\"type\" IN ('DesiredLanguage') AND \"desired_languages_users\".\"user_id\" = 3","name":"DesiredLanguage Load","connection_id":70150201096160,"binds":[]},"time":"2013-07-22T00:39:58-07:00","transaction_id":"c8444315dded90ed8d49","end":"2013-07-22T00:39:58-07:00","duration":0.695},{"name":"sql.active_record","payload":{"sql":"SELECT \"languages\".* FROM \"languages\" INNER JOIN \"desired_languages_users\" ON \"languages\".\"id\" = \"desired_languages_users\".\"desired_language_id\" WHERE \"languages\".\"type\" IN ('DesiredLanguage') AND \"desired_languages_users\".\"user_id\" = 2","name":"DesiredLanguage Load","connection_id":70150201096160,"binds":[]},"time":"2013-07-22T00:39:58-07:00","transaction_id":"c8444315dded90ed8d49","end":"2013-07-22T00:39:58-07:00","duration":0.858},{"name":"sql.active_record","payload":{"sql":"SELECT \"languages\".* FROM \"languages\" INNER JOIN \"desired_languages_users\" ON \"languages\".\"id\" = \"desired_languages_users\".\"desired_language_id\" WHERE \"languages\".\"type\" IN ('DesiredLanguage') AND \"desired_languages_users\".\"user_id\" = 4","name":"DesiredLanguage Load","connection_id":70150201096160,"binds":[]},"time":"2013-07-22T00:39:58-07:00","transaction_id":"c8444315dded90ed8d49","end":"2013-07-22T00:39:58-07:00","duration":0.757},{"name":"sql.active_record","payload":{"sql":"SELECT \"languages\".* FROM \"languages\" INNER JOIN \"desired_languages_users\" ON \"languages\".\"id\" = \"desired_languages_users\".\"desired_language_id\" WHERE \"languages\".\"type\" IN ('DesiredLanguage') AND \"desired_languages_users\".\"user_id\" = 5","name":"DesiredLanguage Load","connection_id":70150201096160,"binds":[]},"time":"2013-07-22T00:39:58-07:00","transaction_id":"c8444315dded90ed8d49","end":"2013-07-22T00:39:58-07:00","duration":0.606},{"name":"sql.active_record","payload":{"sql":"SELECT \"languages\".* FROM \"languages\" INNER JOIN \"desired_languages_users\" ON \"languages\".\"id\" = \"desired_languages_users\".\"desired_language_id\" WHERE \"languages\".\"type\" IN ('DesiredLanguage') AND \"desired_languages_users\".\"user_id\" = 6","name":"DesiredLanguage Load","connection_id":70150201096160,"binds":[]},"time":"2013-07-22T00:39:58-07:00","transaction_id":"c8444315dded90ed8d49","end":"2013-07-22T00:39:58-07:00","duration":0.574},{"name":"sql.active_record","payload":{"sql":"SELECT \"languages\".* FROM \"languages\" INNER JOIN \"desired_languages_users\" ON \"languages\".\"id\" = \"desired_languages_users\".\"desired_language_id\" WHERE \"languages\".\"type\" IN ('DesiredLanguage') AND \"desired_languages_users\".\"user_id\" = 8","name":"DesiredLanguage Load","connection_id":70150201096160,"binds":[]},"time":"2013-07-22T00:39:58-07:00","transaction_id":"c8444315dded90ed8d49","end":"2013-07-22T00:39:58-07:00","duration":0.5640000000000001},{"name":"sql.active_record","payload":{"sql":"SELECT \"languages\".* FROM \"languages\" INNER JOIN \"desired_languages_users\" ON \"languages\".\"id\" = \"desired_languages_users\".\"desired_language_id\" WHERE \"languages\".\"type\" IN ('DesiredLanguage') AND \"desired_languages_users\".\"user_id\" = 9","name":"DesiredLanguage Load","connection_id":70150201096160,"binds":[]},"time":"2013-07-22T00:39:58-07:00","transaction_id":"c8444315dded90ed8d49","end":"2013-07-22T00:39:58-07:00","duration":0.532},{"name":"sql.active_record","payload":{"sql":"SELECT \"languages\".* FROM \"languages\" INNER JOIN \"desired_languages_users\" ON \"languages\".\"id\" = \"desired_languages_users\".\"desired_language_id\" WHERE \"languages\".\"type\" IN ('DesiredLanguage') AND \"desired_languages_users\".\"user_id\" = 1","name":"DesiredLanguage Load","connection_id":70150201096160,"binds":[]},"time":"2013-07-22T00:39:58-07:00","transaction_id":"c8444315dded90ed8d49","end":"2013-07-22T00:39:58-07:00","duration":0.5820000000000001},{"name":"render_template.action_view","payload":{"identifier":"/Users/alexlin/Desktop/WDI/rails_projects/language_network/app/views/users/index.html.haml","layout":"layouts/application"},"time":"2013-07-22T00:39:58-07:00","transaction_id":"6e7e84481be05ff2080e","end":"2013-07-22T00:39:58-07:00","duration":35.702},{"name":"sql.active_record","payload":{"sql":"SELECT  \"users\".* FROM \"users\"  WHERE \"users\".\"id\" = $1 LIMIT 1","name":"User Load","connection_id":70150201096160,"binds":[[{"name":"id","sql_type":"integer","null":false,"limit":null,"precision":null,"scale":null,"type":"integer","default":null,"primary":true,"coder":null},1]]},"time":"2013-07-22T00:39:58-07:00","transaction_id":"c8444315dded90ed8d49","end":"2013-07-22T00:39:58-07:00","duration":0.40900000000000003},{"name":"sql.active_record","payload":{"sql":"SELECT  \"users\".* FROM \"users\"  WHERE \"users\".\"id\" = $1 LIMIT 1","binds":[[{"name":"id","sql_type":"integer","null":false,"limit":null,"precision":null,"scale":null,"type":"integer","default":null,"primary":true,"coder":null},1]],"name":"CACHE","connection_id":70150201096160},"time":"2013-07-22T00:39:58-07:00","transaction_id":"6e7e84481be05ff2080e","end":"2013-07-22T00:39:58-07:00","duration":0.001},{"name":"process_action.action_controller","payload":{"controller":"UsersController","action":"index","params":{"action":"index","controller":"users"},"format":"html","method":"GET","path":"/users","status":200,"view_runtime":82.92099999999999,"db_runtime":6.107},"time":"2013-07-22T00:39:58-07:00","transaction_id":"6e7e84481be05ff2080e","end":"2013-07-22T00:39:58-07:00","duration":90.449}]