[{"name":"sql.active_record","payload":{"sql":"SELECT  \"users\".* FROM \"users\"  WHERE \"users\".\"id\" = $1 LIMIT 1","name":"User Load","connection_id":70150201096160,"binds":[[{"name":"id","sql_type":"integer","null":false,"limit":null,"precision":null,"scale":null,"type":"integer","default":null,"primary":true,"coder":null},1]]},"time":"2013-07-22T02:31:18-07:00","transaction_id":"c8444315dded90ed8d49","end":"2013-07-22T02:31:18-07:00","duration":0.419},{"name":"sql.active_record","payload":{"sql":"SELECT \"messages\".* FROM \"messages\"  WHERE \"messages\".\"receiver_id\" = 1","name":"Message Load","connection_id":70150201096160,"binds":[]},"time":"2013-07-22T02:31:18-07:00","transaction_id":"c8444315dded90ed8d49","end":"2013-07-22T02:31:18-07:00","duration":0.46900000000000003},{"name":"sql.active_record","payload":{"sql":"SELECT  \"users\".* FROM \"users\"  WHERE \"users\".\"id\" = 3 LIMIT 1","name":"User Load","connection_id":70150201096160,"binds":[]},"time":"2013-07-22T02:31:18-07:00","transaction_id":"c8444315dded90ed8d49","end":"2013-07-22T02:31:18-07:00","duration":0.453},{"name":"sql.active_record","payload":{"sql":"SELECT  \"users\".* FROM \"users\"  WHERE \"users\".\"id\" = 2 LIMIT 1","name":"User Load","connection_id":70150201096160,"binds":[]},"time":"2013-07-22T02:31:18-07:00","transaction_id":"c8444315dded90ed8d49","end":"2013-07-22T02:31:18-07:00","duration":0.47300000000000003},{"name":"render_template.action_view","payload":{"identifier":"/Users/alexlin/Desktop/WDI/rails_projects/language_network/app/views/messages/inbox.html.haml","layout":"layouts/application"},"time":"2013-07-22T02:31:18-07:00","transaction_id":"0dc6ed5bc825e4c4158a","end":"2013-07-22T02:31:18-07:00","duration":6.3229999999999995},{"name":"sql.active_record","payload":{"sql":"SELECT  \"users\".* FROM \"users\"  WHERE \"users\".\"id\" = $1 LIMIT 1","binds":[[{"name":"id","sql_type":"integer","null":false,"limit":null,"precision":null,"scale":null,"type":"integer","default":null,"primary":true,"coder":null},1]],"name":"CACHE","connection_id":70150201096160},"time":"2013-07-22T02:31:18-07:00","transaction_id":"0dc6ed5bc825e4c4158a","end":"2013-07-22T02:31:18-07:00","duration":0.001},{"name":"sql.active_record","payload":{"sql":"SELECT  \"users\".* FROM \"users\"  WHERE \"users\".\"id\" = $1 LIMIT 1","binds":[[{"name":"id","sql_type":"integer","null":false,"limit":null,"precision":null,"scale":null,"type":"integer","default":null,"primary":true,"coder":null},1]],"name":"CACHE","connection_id":70150201096160},"time":"2013-07-22T02:31:18-07:00","transaction_id":"0dc6ed5bc825e4c4158a","end":"2013-07-22T02:31:18-07:00","duration":0.001},{"name":"process_action.action_controller","payload":{"controller":"MessagesController","action":"inbox","params":{"controller":"messages","action":"inbox"},"format":"html","method":"GET","path":"/messages/inbox","status":200,"view_runtime":32.81,"db_runtime":1.8159999999999998},"time":"2013-07-22T02:31:18-07:00","transaction_id":"0dc6ed5bc825e4c4158a","end":"2013-07-22T02:31:18-07:00","duration":36.028999999999996}]